matchzoo/__init__.py
matchzoo/embedding.py
matchzoo/logger.py
matchzoo/main.py
matchzoo/version.py
matchzoo/auto/__init__.py
matchzoo/auto/prepare.py
matchzoo/auto/tuner.py
matchzoo/contrib/__init__.py
matchzoo/contrib/layers/__init__.py
matchzoo/contrib/models/__init__.py
matchzoo/contrib/models/match_lstm.py
matchzoo/data_generator/__init__.py
matchzoo/data_generator/data_generator.py
matchzoo/data_generator/dpool_data_generator.py
matchzoo/data_generator/dynamic_data_generator.py
matchzoo/data_generator/histogram_data_generator.py
matchzoo/data_generator/pair_data_generator.py
matchzoo/data_pack/__init__.py
matchzoo/data_pack/build_unit_from_data_pack.py
matchzoo/data_pack/build_vocab_unit.py
matchzoo/data_pack/data_pack.py
matchzoo/data_pack/pack.py
matchzoo/datasets/__init__.py
matchzoo/datasets/embeddings/__init__.py
matchzoo/datasets/embeddings/load_glove_embedding.py
matchzoo/datasets/snli/__init__.py
matchzoo/datasets/snli/load_data.py
matchzoo/datasets/toy/__init__.py
matchzoo/datasets/wiki_qa/__init__.py
matchzoo/datasets/wiki_qa/load_data.py
matchzoo/engine/__init__.py
matchzoo/engine/base_metric.py
matchzoo/engine/base_model.py
matchzoo/engine/base_preprocessor.py
matchzoo/engine/base_task.py
matchzoo/engine/callbacks.py
matchzoo/engine/hyper_spaces.py
matchzoo/engine/param.py
matchzoo/engine/param_table.py
matchzoo/inputs/__init__.py
matchzoo/inputs/list_generator.py
matchzoo/inputs/pair_generator.py
matchzoo/inputs/point_generator.py
matchzoo/inputs/preparation.py
matchzoo/inputs/preprocess.py
matchzoo/layers/BiLSTM.py
matchzoo/layers/DynamicMaxPooling.py
matchzoo/layers/Match.py
matchzoo/layers/MatchTensor.py
matchzoo/layers/MultiPerspectiveMatch.py
matchzoo/layers/NonMasking.py
matchzoo/layers/SequenceMask.py
matchzoo/layers/SparseFullyConnectedLayer.py
matchzoo/layers/SpatialGRU.py
matchzoo/layers/__init__.py
matchzoo/layers/dynamic_pooling_layer.py
matchzoo/layers/matching_layer.py
matchzoo/losses/__init__.py
MatchZoo-1.0.0.dist-info/LICENSE
MatchZoo-1.0.0.dist-info/METADATA
MatchZoo-1.0.0.dist-info/WHEEL
MatchZoo-1.0.0.dist-info/top_level.txt
MatchZoo-1.0.0.dist-info/RECORD
